sewinger/__init__.py
sewinger-0.1.2.dist-info/METADATA
sewinger-0.1.2.dist-info/WHEEL
sewinger-0.1.2.dist-info/RECORD
