Metadata-Version: 2.1
Name: sewinger
Version: 0.1.2
Summary: A simple, lightweight Python dependency injection framework. Get sewing right away.
License: MIT
Author: goddessana
Author-email: twicegoddessana1229@gmail.com
Requires-Python: >=3.9,<4.0
Classifier: License :: OSI Approved :: MIT License
Classifier: Programming Language :: Python :: 3
Classifier: Programming Language :: Python :: 3.9
Classifier: Programming Language :: Python :: 3.10
Classifier: Programming Language :: Python :: 3.11
Classifier: Programming Language :: Python :: 3.12
